hwin/main.py
hwin-10.10.10.dist-info/METADATA
hwin-10.10.10.dist-info/WHEEL
hwin-10.10.10.dist-info/entry_points.txt
hwin-10.10.10.dist-info/RECORD
